nal_sys.py
Nal_sys-0.0.1.dist-info/METADATA
Nal_sys-0.0.1.dist-info/WHEEL
Nal_sys-0.0.1.dist-info/top_level.txt
Nal_sys-0.0.1.dist-info/RECORD
