Metadata-Version: 2.1
Name: Nal-sys
Version: 0.0.1
Summary: This is a libery for numerical anlysis, most common tools for the Bachlor program in physics.
Home-page: UNKNOWN
Author: Andreas Evensen
Author-email: Andreas.evensen11@gmail.com
License: MIT
Keywords: Numerical Anlysis
Platform: UNKNOWN
Classifier: Development Status :: 3 - Alpha
Classifier: Intended Audience :: Developers
Classifier: License :: OSI Approved :: MIT License
